dls_python3_skeleton/__init__.py
dls_python3_skeleton/__main__.py
dls_python3_skeleton/_version_git.py
dls_python3_skeleton-1.4.dist-info/LICENSE
dls_python3_skeleton-1.4.dist-info/METADATA
dls_python3_skeleton-1.4.dist-info/WHEEL
dls_python3_skeleton-1.4.dist-info/entry_points.txt
dls_python3_skeleton-1.4.dist-info/top_level.txt
dls_python3_skeleton-1.4.dist-info/RECORD
